tracker/__init__.py
tracker/cli/__init__.py
tracker/cli/interntrack/__init__.py
tracker/cli/interntrack/request.py
tracker/cli/jenkins/__init__.py
tracker/cli/jenkins/request.py
tracker/lib/__init__.py
tracker/lib/InternTrain/__init__.py
tracker/lib/InternTrain/distributed_merge.py
tracker/lib/InternTrain/load_train_state.py
tracker/model/__init__.py
tracker/model/models.py
tracker/utils/__init__.py
tracker/utils/hash.py
tracker/utils/load_url.py
tracker/utils/process_md5.py
interntracker-0.0.7.dist-info/LICENSE
interntracker-0.0.7.dist-info/METADATA
interntracker-0.0.7.dist-info/WHEEL
interntracker-0.0.7.dist-info/top_level.txt
interntracker-0.0.7.dist-info/RECORD
